rpbp/__init__.py
rpbp/defaults.py
rpbp/run_all_rpbp_instances.py
rpbp/run_rpbp_pipeline.py
rpbp/analysis/__init__.py
rpbp/analysis/profile_construction/__init__.py
rpbp/analysis/profile_construction/collect_read_length_orf_profiles.py
rpbp/analysis/profile_construction/create_read_length_orf_profiles.py
rpbp/analysis/profile_construction/get_all_read_filtering_counts.py
rpbp/analysis/profile_construction/summarize_rpbp_profile_construction.py
rpbp/analysis/profile_construction/visualize_metagene_profile_bayes_factor.py
rpbp/analysis/profile_construction/dashboard/__init__.py
rpbp/analysis/profile_construction/dashboard/controls.py
rpbp/analysis/profile_construction/dashboard/rpbp_profile_construction_dashboard.py
rpbp/analysis/profile_construction/dashboard/assets/logo-rpbp.png
rpbp/analysis/profile_construction/dashboard/assets/style.css
rpbp/analysis/proteomics/__init__.py
rpbp/analysis/proteomics/filter_nonunique_peptide_matches.py
rpbp/analysis/proteomics/get_orf_peptide_matches.py
rpbp/analysis/rpbp_predictions/__init__.py
rpbp/analysis/rpbp_predictions/summarize_rpbp_predictions.py
rpbp/analysis/rpbp_predictions/visualize_orf_type_metagene_profiles.py
rpbp/analysis/rpbp_predictions/dashboard/__init__.py
rpbp/analysis/rpbp_predictions/dashboard/rpbp_predictions_dashboard.py
rpbp/analysis/rpbp_predictions/dashboard/assets/logo-rpbp.png
rpbp/analysis/rpbp_predictions/dashboard/assets/schematic.png
rpbp/analysis/rpbp_predictions/dashboard/assets/style.css
rpbp/models/__init__.py
rpbp/models/nonperiodic/__init__.py
rpbp/models/nonperiodic/no-periodicity.stan
rpbp/models/nonperiodic/start-high-high-low.stan
rpbp/models/nonperiodic/start-high-low-high.stan
rpbp/models/periodic/__init__.py
rpbp/models/periodic/start-high-low-low.stan
rpbp/models/translated/__init__.py
rpbp/models/translated/periodic-gaussian-mixture.stan
rpbp/models/untranslated/__init__.py
rpbp/models/untranslated/gaussian-naive-bayes.stan
rpbp/orf_profile_construction/__init__.py
rpbp-4.0.0.dist-info/licenses/LICENSE
rpbp-4.0.0.dist-info/METADATA
rpbp-4.0.0.dist-info/WHEEL
rpbp-4.0.0.dist-info/entry_points.txt
rpbp-4.0.0.dist-info/top_level.txt
rpbp-4.0.0.dist-info/RECORD
