Metadata-Version: 2.4
Name: rpbp
Version: 4.0.0
Summary: Rp-Bp: Ribosome Profiling with Bayesian Predictions
Author: Brandon Malone
Maintainer-email: Etienne Boileau <boileau@uni-heidelberg.de>
License-Expression: MIT
Project-URL: Github, https://github.com/dieterich-lab/rp-bp
Project-URL: Issues, https://github.com/dieterich-lab/rp-bp/issues
Keywords: Bioinformatics,Ribo-seq/Ribosome profiling quality control,Open reading frame (ORF) discovery,Translation prediction
Classifier: Development Status :: 5 - Production/Stable
Classifier: Intended Audience :: Science/Research
Classifier: Topic :: Scientific/Engineering :: Bio-Informatics
Classifier: Operating System :: MacOS :: MacOS X
Classifier: Operating System :: POSIX :: Linux
Classifier: Programming Language :: Python :: 3.11
Classifier: Programming Language :: Python :: 3.12
Classifier: Programming Language :: Python :: 3.13
Requires-Python: <3.14,>=3.11
License-File: LICENSE
Requires-Dist: pbiotools>=5.0.0
Requires-Dist: appdirs
Requires-Dist: cmdstanpy
Requires-Dist: dash
Requires-Dist: dash-bio
Requires-Dist: dash-bootstrap-components
Requires-Dist: pyyaml
Requires-Dist: statsmodels
Provides-Extra: tests
Requires-Dist: pytest; extra == "tests"
Requires-Dist: pytest-cov; extra == "tests"
Requires-Dist: pytest-depends; extra == "tests"
Provides-Extra: docs
Requires-Dist: ipykernel; extra == "docs"
Requires-Dist: matplotlib; extra == "docs"
Requires-Dist: nbsphinx; extra == "docs"
Requires-Dist: pandoc; extra == "docs"
Requires-Dist: sphinx; extra == "docs"
Requires-Dist: sphinx_rtd_theme; extra == "docs"
Requires-Dist: furo; extra == "docs"
Requires-Dist: sphinx-argparse; extra == "docs"
Requires-Dist: sphinx-copybutton; extra == "docs"
Dynamic: license-file
